cltoolbox/__init__.py
cltoolbox/cltoolbox.py
cltoolbox/rst_text_formatter.py
cltoolbox/python_rst2ansi/setup.py
cltoolbox/python_rst2ansi/rst2ansi/__init__.py
cltoolbox/python_rst2ansi/rst2ansi/ansi.py
cltoolbox/python_rst2ansi/rst2ansi/functional.py
cltoolbox/python_rst2ansi/rst2ansi/table.py
cltoolbox/python_rst2ansi/rst2ansi/unicode.py
cltoolbox/python_rst2ansi/rst2ansi/visitor.py
cltoolbox/python_rst2ansi/rst2ansi/wrap.py
cltoolbox-4.0.0.dist-info/licenses/LICENSE.txt
cltoolbox-4.0.0.dist-info/METADATA
cltoolbox-4.0.0.dist-info/WHEEL
cltoolbox-4.0.0.dist-info/top_level.txt
cltoolbox-4.0.0.dist-info/RECORD
