Metadata-Version: 2.4
Name: cltoolbox
Version: 4.0.0
Summary: Python library for creating and manipulating CLIs
Author-email: Tim Cera <tim@cerazone.net>
License: BSD-3-Clause and MIT
Project-URL: documentation, https://timcera.bitbucket.io/cltoolbox/docs/index.html#cltoolbox-documentation
Project-URL: github, https://github.com/timcera/cltoolbox
Project-URL: bitbucket, https://bitbucket.org/timcera/cltoolbox/src/main/
Keywords: python,cli,argparse,arguments,command line,keyword arguments,docstring
Classifier: Development Status :: 5 - Production/Stable
Classifier: Intended Audience :: End Users/Desktop
Classifier: Intended Audience :: Developers
Classifier: Environment :: Console
Classifier: License :: OSI Approved :: BSD License
Classifier: License :: OSI Approved :: MIT License
Classifier: Natural Language :: English
Classifier: Operating System :: OS Independent
Classifier: Programming Language :: Python :: 3 :: Only
Classifier: Programming Language :: Python :: 3.8
Classifier: Programming Language :: Python :: 3.9
Classifier: Programming Language :: Python :: 3.10
Classifier: Programming Language :: Python :: 3.11
Classifier: Programming Language :: Python :: 3.12
Classifier: Programming Language :: Python :: 3.13
Classifier: Topic :: Software Development :: Libraries :: Python Modules
License-File: LICENSE.txt
Requires-Dist: docstring_parser
Requires-Dist: docutils
Dynamic: license-file
